SuiBotProject/TEST.py
SuiBotProject/__init__.py
SuiBotProject-1.0.0.dist-info/LICENSE
SuiBotProject-1.0.0.dist-info/METADATA
SuiBotProject-1.0.0.dist-info/WHEEL
SuiBotProject-1.0.0.dist-info/top_level.txt
SuiBotProject-1.0.0.dist-info/RECORD
