Metadata-Version: 2.1
Name: SuiBotProject
Version: 1.0.0
Summary: Sui Bot package
Home-page: https://github.com/DreamBreakk/SuiBotProject
Author: Kujira
Author-email: nopemo93@gmail.com
Project-URL: Documentation, https://github.com/DreamBreakk/SuiBotProject
Project-URL: Source, https://github.com/DreamBreakk/SuiBotProject
Keywords: BetFuryBotProject
Classifier: Programming Language :: Python :: 3.12
Classifier: License :: OSI Approved :: MIT License
Classifier: Operating System :: OS Independent
Requires-Python: >=3.7
License-File: LICENSE
Requires-Dist: requests >=2.25.1
